Metadata-Version: 2.1
Name: annotation_conversions
Version: 0.2.7
Summary: Converts one annotation format to another in a single step
Home-page: https://github.com/beatboxerish/labelme2coco
Download-URL: https://github.com/beatboxerish/labelme2coco/archive/refs/tags/v0.2.6.tar.gz
Author: Ishan Nangia
Author-email: ishannangia.123@gmail.com
Classifier: Programming Language :: Python :: 3
Classifier: License :: OSI Approved :: MIT License
Classifier: Operating System :: OS Independent
Requires-Python: >=3.7
License-File: LICENSE
Requires-Dist: sahi>=0.8.19
Requires-Dist: jsonschema>=2.6.0
